{
  "name": "Demographie",
  "color": "#8C2DA7",
  "items": [
    {
      "objectId": "Population",
      "objectType": "DATASET"
    },
    {
      "objectId": "Nombre_enfant",
      "objectType": "DATASET"
    },
    {
      "objectId": "Nombre_dimmigre",
      "objectType": "DATASET"
    },
    {
      "objectId": "Nombre_detranger",
      "objectType": "DATASET"
    },
    {
      "objectId": "Evolution_population",
      "objectType": "DATASET"
    },
    {
      "objectId": "Repartition_age",
      "objectType": "DATASET"
    },
    {
      "objectId": "Repartition_sexe",
      "objectType": "DATASET"
    },
    {
      "objectId": "MSPR_Evolution_population",
      "objectType": "DATASET"
    },
    {
      "objectId": "MSPR_Nombre_detranger",
      "objectType": "DATASET"
    },
    {
      "objectId": "MSPR_Nombre_dimmigre",
      "objectType": "DATASET"
    },
    {
      "objectId": "MSPR_Nombre_enfant",
      "objectType": "DATASET"
    },
    {
      "objectId": "MSPR_Population",
      "objectType": "DATASET"
    },
    {
      "objectId": "MSPR_Repartition_age",
      "objectType": "DATASET"
    },
    {
      "objectId": "MSPR_Repartition_sexe",
      "objectType": "DATASET"
    },
    {
      "objectId": "compute_criteres",
      "objectType": "RECIPE"
    },
    {
      "objectId": "Taux_de_natalite",
      "objectType": "DATASET"
    },
    {
      "objectId": "Composition_menage",
      "objectType": "DATASET"
    },
    {
      "objectId": "Taux_scolarisation",
      "objectType": "DATASET"
    },
    {
      "objectId": "Logement",
      "objectType": "DATASET"
    },
    {
      "objectId": "Repartition_des_contrats",
      "objectType": "DATASET"
    },
    {
      "objectId": "Taux_de_chomage",
      "objectType": "DATASET"
    },
    {
      "objectId": "Delinquance",
      "objectType": "DATASET"
    },
    {
      "objectId": "Salaire_moyen",
      "objectType": "DATASET"
    },
    {
      "objectId": "Type_logement",
      "objectType": "DATASET"
    },
    {
      "objectId": "Statut_occupation_logement",
      "objectType": "DATASET"
    },
    {
      "objectId": "Nombre_de_salarie",
      "objectType": "DATASET"
    },
    {
      "objectId": "Taux_de_pauvrete",
      "objectType": "DATASET"
    },
    {
      "objectId": "Categorie_logement",
      "objectType": "DATASET"
    },
    {
      "objectId": "Taux_de_mortalite",
      "objectType": "DATASET"
    },
    {
      "objectId": "Administration_penitentiaire",
      "objectType": "DATASET"
    },
    {
      "objectId": "Impot_moyen",
      "objectType": "DATASET"
    },
    {
      "objectId": "aPmnwurD",
      "objectType": "MANAGED_FOLDER"
    }
  ],
  "shared": [],
  "tags": [],
  "customFields": {},
  "checklists": {
    "checklists": []
  }
}